{
  "main": {
    "id": "158c90f999367fcf",
    "type": "split",
    "children": [
      {
        "id": "f1618f789420b486",
        "type": "tabs",
        "children": [
          {
            "id": "3cc77370206ce44b",
            "type": "leaf",
            "state": {
              "type": "markdown",
              "state": {
                "file": "代数学/Book 1. 矩阵代数/Chapter 1. 基本概念/Lecture 1. 矩阵的基.md",
                "mode": "source",
                "backlinks": true,
                "source": false
              }
            }
          }
        ]
      }
    ],
    "direction": "vertical"
  },
  "left": {
    "id": "f91c5cae2f6cc636",
    "type": "split",
    "children": [
      {
        "id": "1350d3288a9e97c3",
        "type": "tabs",
        "children": [
          {
            "id": "1540de2207820773",
            "type": "leaf",
            "state": {
              "type": "file-explorer",
              "state": {
                "sortOrder": "alphabetical"
              }
            }
          },
          {
            "id": "bbc36c3718db1e11",
            "type": "leaf",
            "state": {
              "type": "search",
              "state": {
                "query": "",
                "matchingCase": true,
                "explainSearch": false,
                "collapseAll": false,
                "extraContext": false,
                "sortOrder": "alphabetical"
              }
            }
          },
          {
            "id": "dd44aabb805f5508",
            "type": "leaf",
            "state": {
              "type": "starred",
              "state": {}
            }
          },
          {
            "id": "7fb264b260c91e16",
            "type": "leaf",
            "state": {
              "type": "bookmarks",
              "state": {}
            }
          }
        ]
      }
    ],
    "direction": "horizontal",
    "width": 343.504695892334
  },
  "right": {
    "id": "45b6cc51caac60ea",
    "type": "split",
    "children": [
      {
        "id": "4acbe99a6d909605",
        "type": "tabs",
        "children": [
          {
            "id": "75efd8ef3626eec0",
            "type": "leaf",
            "state": {
              "type": "backlink",
              "state": {
                "file": "代数学/Book 1. 矩阵代数/Chapter 1. 基本概念/Lecture 1. 矩阵的基.md",
                "collapseAll": false,
                "extraContext": false,
                "sortOrder": "alphabetical",
                "showSearch": false,
                "searchQuery": "",
                "backlinkCollapsed": false,
                "unlinkedCollapsed": true
              }
            }
          },
          {
            "id": "77b7881659bc9657",
            "type": "leaf",
            "state": {
              "type": "outgoing-link",
              "state": {
                "file": "代数学/Book 1. 矩阵代数/Chapter 1. 基本概念/Lecture 1. 矩阵的基.md",
                "linksCollapsed": false,
                "unlinkedCollapsed": true
              }
            }
          },
          {
            "id": "096966112e87e6b7",
            "type": "leaf",
            "state": {
              "type": "tag",
              "state": {
                "sortOrder": "frequency",
                "useHierarchy": true
              }
            }
          },
          {
            "id": "c0cb9946f3baa9db",
            "type": "leaf",
            "state": {
              "type": "outline",
              "state": {
                "file": "代数学/Book 1. 矩阵代数/Chapter 1. 基本概念/Lecture 1. 矩阵的基.md"
              }
            }
          },
          {
            "id": "50e0d03ce6fe455a",
            "type": "leaf",
            "state": {
              "type": "advanced-tables-toolbar",
              "state": {}
            }
          }
        ]
      }
    ],
    "direction": "horizontal",
    "width": 200,
    "collapsed": true
  },
  "left-ribbon": {
    "hiddenItems": {
      "switcher:打开快速切换": false,
      "graph:查看关系图谱": false,
      "canvas:新建白板": false,
      "daily-notes:打开/创建今天的日记": false,
      "templates:插入模板": false,
      "command-palette:打开命令面板": false,
      "markdown-importer:打开 Markdown 格式转换器": false,
      "table-editor-obsidian:Advanced Tables Toolbar": false
    }
  },
  "active": "3cc77370206ce44b",
  "lastOpenFiles": [
    "代数学/Book 1. 矩阵代数/Chapter 1. 基本概念/Lecture 3. 矩阵分块.md",
    "代数学/Book 1. 矩阵代数/Chapter 1. 基本概念/Lecture 4. 内积与范数.md",
    "代数学/Book 1. 矩阵代数/Chapter 1. 基本概念/Lecture 1. 矩阵的基.md",
    "代数学/Book 1. 矩阵代数/Chapter 1. 线性代数/Lecture 1. 内积和范数.md",
    "代数学/Book 1. 矩阵代数/Chapter 1. 基本概念/Lecture 1. 矩阵的秩.md",
    "代数学/Book 1. 矩阵代数/Chapter 1. 基本概念/Lecture 4. 特殊矩阵.md",
    "代数学/Book 1. 矩阵代数/Chapter 1. 基本概念/Lecture 5. 内积与范数.md",
    "代数学/Book 1. 矩阵代数/Chapter 1. 基本概念/Lecture 5. 内积与范数",
    "代数学/Book 1. 矩阵代数/Chapter 1. 基本概念/Lecture 3. 分块矩阵.md",
    "代数学/Book 1. 矩阵代数/Chapter 1. 基本概念/Lecture 2. 行列式.md",
    "代数学/Book 1. 矩阵代数/Chapter 1. 基本概念/Lecture 3. 特殊矩阵.md",
    "代数学/Book 1. 矩阵代数/Chapter 1. 基本概念/Lecture 1. 基本概念.md",
    "代数学/Book 1. 矩阵代数/Chapter 1. 线性代数/Lecture 1. 基本概念.md",
    "PKU Learning Notes/博弈论/Lecture 9. 讨价还价.md",
    "PKU Learning Notes/社会科学中的计算思维方法/Lecture 2. 小世界与扩散.md",
    "PKU Learning Notes/社会科学中的计算思维方法/Lecture 3. 博弈论的应用.md",
    "PKU Learning Notes/社会科学中的计算思维方法/Lecture 5. 信息聚合行为.md",
    "PKU Learning Notes/社会科学中的计算思维方法/Lecture 4. 万维网和搜索引擎.md",
    "PKU Learning Notes/社会科学中的计算思维方法/Lecture 1. 关系的平衡和议价.md",
    "PKU Learning Notes/博弈论/Lecture 9. 讨价还价.assets/平衡结果.png",
    "重要方法/Normalization of Neural Network.md",
    "重要方法/Initialization of Neural Network.md",
    "PKU Learning Notes/博弈论/Lecture 14. 稳定匹配.md",
    "PKU Learning Notes/博弈论/Lecture 13. 社会选择.md",
    "theme.css",
    "PKU Learning Notes/博弈论/Lecture 13. 社会选择与稳定匹配.md",
    "重要方法/Domain Adaptation.md",
    "PKU Learning Notes/博弈论/Lecture 13. 社会选择.assets/偏好关系的拼接.png",
    "Lecture 13. 社会选择与稳定匹配.assets/Z(P%2C Q%3B R).png.md",
    "Lecture 13. 社会选择与稳定匹配.assets",
    "PKU Learning Notes/博弈论/Lecture 4. 均衡(扩展式博弈).md",
    "PKU Learning Notes/博弈论/Lecture 5. 知识的层级.assets/Aumann同意一个例子.png",
    "PKU Learning Notes/博弈论/Lecture 5. 知识的层级.assets/Aumann同意定理一个例子.png",
    "PKU Learning Notes/博弈论/Lecture 5. 知识的层级.assets",
    "PKU Learning Notes/博弈论/Lecture 3. 均衡(策略式博弈).assets/相关机制的斗鸡博弈.png",
    "PKU Learning Notes/博弈论/Lecture 4. 均衡(扩展式博弈).html",
    "PKU Learning Notes/博弈论/Lecture 4. 均衡(扩展式博弈).assets/行为策略没有等价的混合策略.png",
    "PKU Learning Notes/博弈论/Lecture 4. 均衡(扩展式博弈).assets/${filename}.png",
    "PKU Learning Notes/博弈论/Lecture 4. 均衡(扩展式博弈).assets/混合策略没有等价的行为策略.png",
    "PKU Learning Notes/博弈论/Lecture 4. 均衡(扩展式博弈).pdf",
    "代数学/Book 1. 矩阵代数/Chapter 1. 基本概念/Lecture 1. 矩阵.html",
    "代数学/Book 1. 矩阵代数/Chapter 1. 基本概念",
    "PKU Learning Notes/博弈论/Lecture 10. 拍卖.html",
    "PKU Learning Notes/博弈论/Lecture 9. 讨价还价.html",
    "PKU Learning Notes/博弈论/Lecture 4. 均衡(扩展式博弈).assets/子博弈完美均衡未必是扩展式完美均衡.png",
    "PKU Learning Notes/博弈论/Lecture 9. 讨价还价.assets/lambda_alpha.png",
    "未命名.canvas"
  ]
}